Metadata-Version: 2.4
Name: llama-index-packs-zephyr-query-engine
Version: 0.5.1
Summary: llama-index packs zephyr_query_engine integration
Author-email: Your Name <you@example.com>
Maintainer: logan-markewich
License-Expression: MIT
License-File: LICENSE
Keywords: engine,huggingface,index,local,query,zephyr
Requires-Python: <4.0,>=3.9
Requires-Dist: accelerate<0.27,>=0.26.1
Requires-Dist: bitsandbytes<0.43,>=0.42.0
Requires-Dist: llama-index-core<0.15,>=0.13.0
Requires-Dist: llama-index-llms-huggingface<0.7,>=0.6.0
Requires-Dist: torch<3,>=2.1.2
Requires-Dist: transformers<5,>=4.37.1
